LICENSE
MANIFEST.in
PYPI_README.md
README.md
config.env
pyproject.toml
requirements.txt
setup.py
admin/app.js
admin/auth.js
admin/index.html
examples/basic_usage.py
pyhybriddb/__init__.py
pyhybriddb/cli.py
pyhybriddb/config.py
pyhybriddb.egg-info/PKG-INFO
pyhybriddb.egg-info/SOURCES.txt
pyhybriddb.egg-info/dependency_links.txt
pyhybriddb.egg-info/entry_points.txt
pyhybriddb.egg-info/not-zip-safe
pyhybriddb.egg-info/requires.txt
pyhybriddb.egg-info/top_level.txt
pyhybriddb/api/__init__.py
pyhybriddb/api/auth.py
pyhybriddb/api/models.py
pyhybriddb/api/server.py
pyhybriddb/api/users.py
pyhybriddb/core/__init__.py
pyhybriddb/core/collection.py
pyhybriddb/core/connection.py
pyhybriddb/core/database.py
pyhybriddb/core/table.py
pyhybriddb/migration/__init__.py
pyhybriddb/migration/mongodb.py
pyhybriddb/migration/postgresql.py
pyhybriddb/query/__init__.py
pyhybriddb/query/executor.py
pyhybriddb/query/joins.py
pyhybriddb/query/nosql_parser.py
pyhybriddb/query/parser.py
pyhybriddb/query/sql_parser.py
pyhybriddb/storage/__init__.py
pyhybriddb/storage/engine.py
pyhybriddb/storage/file_manager.py
pyhybriddb/storage/index.py
pyhybriddb/utils/__init__.py
pyhybriddb/utils/audit.py
pyhybriddb/utils/backup.py
pyhybriddb/utils/encryption.py
pyhybriddb/utils/logger.py
pyhybriddb/utils/serializer.py
pyhybriddb/utils/visualization.py
venv/Lib/site-packages/__editable___pyhybriddb_0_1_0_finder.py
venv/Lib/site-packages/six.py
venv/Lib/site-packages/typing_extensions.py
venv/Lib/site-packages/_distutils_hack/__init__.py
venv/Lib/site-packages/_distutils_hack/override.py
venv/Lib/site-packages/_yaml/__init__.py
venv/Lib/site-packages/aiofiles/__init__.py
venv/Lib/site-packages/aiofiles/base.py
venv/Lib/site-packages/aiofiles/os.py
venv/Lib/site-packages/aiofiles/ospath.py
venv/Lib/site-packages/aiofiles/tempfile/__init__.py
venv/Lib/site-packages/aiofiles/tempfile/temptypes.py
venv/Lib/site-packages/aiofiles/threadpool/__init__.py
venv/Lib/site-packages/aiofiles/threadpool/binary.py
venv/Lib/site-packages/aiofiles/threadpool/text.py
venv/Lib/site-packages/aiofiles/threadpool/utils.py
venv/Lib/site-packages/annotated_types/__init__.py
venv/Lib/site-packages/annotated_types/py.typed
