Metadata-Version: 2.4
Name: pyhybriddb
Version: 1.0.1
Summary: A production-ready hybrid database system combining SQL and NoSQL with enterprise features
Home-page: https://github.com/Adrient-tech/PyHybridDB
Author: Infant Nirmal
Author-email: Infant Nirmal <contact@adrient.com>
Maintainer-email: Infant Nirmal <contact@adrient.com>
License: MIT
Project-URL: Homepage, https://github.com/Adrient-tech/PyHybridDB
Project-URL: Documentation, https://github.com/Adrient-tech/PyHybridDB#readme
Project-URL: Repository, https://github.com/Adrient-tech/PyHybridDB
Project-URL: Bug Tracker, https://github.com/Adrient-tech/PyHybridDB/issues
Keywords: database,hybrid,sql,nosql,mongodb,postgresql,fastapi,rest-api,backup,audit,encryption
Classifier: Development Status :: 5 - Production/Stable
Classifier: Intended Audience :: Developers
Classifier: Topic :: Database
Classifier: Topic :: Database :: Database Engines/Servers
Classifier: Topic :: Software Development :: Libraries :: Python Modules
Classifier: License :: OSI Approved :: MIT License
Classifier: Programming Language :: Python :: 3
Classifier: Programming Language :: Python :: 3.10
Classifier: Programming Language :: Python :: 3.11
Classifier: Programming Language :: Python :: 3.12
Classifier: Operating System :: OS Independent
Classifier: Environment :: Web Environment
Classifier: Framework :: FastAPI
Requires-Python: >=3.10
License-File: LICENSE
Requires-Dist: fastapi>=0.104.1
Requires-Dist: uvicorn[standard]>=0.24.0
Requires-Dist: pydantic[email]>=2.5.0
Requires-Dist: python-multipart>=0.0.6
Requires-Dist: python-jose[cryptography]>=3.3.0
Requires-Dist: passlib[bcrypt]>=1.7.4
Requires-Dist: sqlparse>=0.4.4
Requires-Dist: aiofiles>=23.2.1
Requires-Dist: python-dotenv>=1.0.0
Requires-Dist: bcrypt>=4.1.1
Requires-Dist: cryptography>=41.0.7
Requires-Dist: email-validator>=2.1.0
Provides-Extra: postgresql
Requires-Dist: psycopg2-binary>=2.9.9; extra == "postgresql"
Provides-Extra: mongodb
Requires-Dist: pymongo>=4.6.0; extra == "mongodb"
Provides-Extra: all
Requires-Dist: psycopg2-binary>=2.9.9; extra == "all"
Requires-Dist: pymongo>=4.6.0; extra == "all"
Provides-Extra: dev
Requires-Dist: pytest>=7.4.0; extra == "dev"
Requires-Dist: pytest-asyncio>=0.21.0; extra == "dev"
Requires-Dist: black>=23.7.0; extra == "dev"
Requires-Dist: flake8>=6.1.0; extra == "dev"
Requires-Dist: mypy>=1.5.0; extra == "dev"
Dynamic: author
Dynamic: home-page
Dynamic: license-file
Dynamic: requires-python
